openai_tools_decorator/__init__.py
openai_tools_decorator/main.py
openai_tools_decorator/meta.py
openai_tools_decorator-1.0.3.dist-info/METADATA
openai_tools_decorator-1.0.3.dist-info/WHEEL
openai_tools_decorator-1.0.3.dist-info/licenses/LICENSE
openai_tools_decorator-1.0.3.dist-info/RECORD
